verthash.cp39-win_amd64.pyd
verthash_test-0.0.2.dist-info/LICENSE
verthash_test-0.0.2.dist-info/METADATA
verthash_test-0.0.2.dist-info/WHEEL
verthash_test-0.0.2.dist-info/top_level.txt
verthash_test-0.0.2.dist-info/RECORD
