Metadata-Version: 2.1
Name: verthash_test
Version: 0.0.2
Summary: Python bindings for Verthash proof of work function
Home-page: https://github.com/vertiond/lyra2re-hash-python
Author: vertion
Author-email: vertion@protonmail.com
License: UNKNOWN
Platform: UNKNOWN
License-File: LICENSE
